cli
gittalk
