Metadata-Version: 1.1
Name: git-talk
Version: 0.0.8a0
Summary: Audio & video annotations for your code with Git!
Home-page: https://github.com/sandeepraju/git-talk
Author: Team Git Talk
Author-email: gittalk338@gmail.com
License: BSD 3-Clause License
